codemagic/__init__.py
codemagic/apps.py
codemagic/builds.py
codemagic/codemagic.py
codemagic/enums.py
codemagic/utils.py
codemagic-1.1.4.dist-info/LICENSE
codemagic-1.1.4.dist-info/METADATA
codemagic-1.1.4.dist-info/WHEEL
codemagic-1.1.4.dist-info/top_level.txt
codemagic-1.1.4.dist-info/RECORD
